LICENSE
MANIFEST.in
README.md
setup.cfg
setup.py
bin/gcalvault
gcalvault.egg-info/PKG-INFO
gcalvault.egg-info/SOURCES.txt
gcalvault.egg-info/dependency_links.txt
gcalvault.egg-info/requires.txt
gcalvault.egg-info/top_level.txt
src/gcalvault/USAGE.txt
src/gcalvault/VERSION.txt
src/gcalvault/__init__.py
src/gcalvault/etag_manager.py
src/gcalvault/gcalvault.py
src/gcalvault/git_vault_repo.py
src/gcalvault/google_oauth2.py
tests/test_gcalvault.py