Metadata-Version: 2.4
Name: gcalvault
Version: 2.0.0
Summary: Command-line utility which exports all of a user's Google Calendars to iCal/ICS format for backup (or portability)
Home-page: http://github.com/rtomac/gcalvault
Author: Ryan Tomac
Author-email: ryan@tomacfamily.com
License: MIT
Keywords: Google Calendar,gcal,backup,export,iCal,ICS,CalDav
Classifier: Development Status :: 5 - Production/Stable
Classifier: Environment :: Console
Classifier: Intended Audience :: End Users/Desktop
Classifier: Natural Language :: English
Classifier: License :: OSI Approved :: MIT License
Classifier: Programming Language :: Python :: 3
Classifier: Programming Language :: Python :: 3.9
Classifier: Topic :: System :: Archiving :: Backup
Requires-Python: >=3.9
License-File: LICENSE
Requires-Dist: google-api-python-client==2.181.*
Requires-Dist: google-auth-httplib2==0.2.*
Requires-Dist: google-auth-oauthlib==1.2.*
Requires-Dist: requests==2.32.*
Requires-Dist: GitPython==3.1.*
Requires-Dist: python-dotenv==1.1.*
Provides-Extra: dev
Requires-Dist: pycodestyle; extra == "dev"
Requires-Dist: setuptools; extra == "dev"
Provides-Extra: test
Requires-Dist: pytest==8.*; extra == "test"
Provides-Extra: release
Requires-Dist: twine; extra == "release"
Dynamic: author
Dynamic: author-email
Dynamic: classifier
Dynamic: description
Dynamic: description-content-type
Dynamic: home-page
Dynamic: keywords
Dynamic: license
Dynamic: license-file
Dynamic: provides-extra
Dynamic: requires-dist
Dynamic: requires-python
Dynamic: summary
